ListOperations.py
__init__.py
test.py
ListRevFunctions-0.1.4.dist-info/LICENSE
ListRevFunctions-0.1.4.dist-info/METADATA
ListRevFunctions-0.1.4.dist-info/WHEEL
ListRevFunctions-0.1.4.dist-info/top_level.txt
ListRevFunctions-0.1.4.dist-info/RECORD
